{"name":"build-javascript","namedChunkGroups":{"app":{"name":"app","assets":[{"name":"webpack-runtime-e0c745ab160e06106336.js","size":3790},{"name":"framework-d3538fe65447818bc523.js","size":140769},{"name":"styles.da9a523e30d00bd413e8.css","size":9917},{"name":"app-924d945b4d9342038a0b.js","size":61516}],"filteredAssets":0,"assetsSize":215992,"filteredAuxiliaryAssets":5,"auxiliaryAssetsSize":1006524},"component---src-pages-404-tsx":{"name":"component---src-pages-404-tsx","assets":[{"name":"cb355538-30fa29680f15d123c598.js","size":4084},{"name":"component---src-pages-404-tsx-18d03eee48b374ad9661.js","size":6273}],"filteredAssets":0,"assetsSize":10357,"filteredAuxiliaryAssets":2,"auxiliaryAssetsSize":1432418},"component---src-pages-about-tsx":{"name":"component---src-pages-about-tsx","assets":[{"name":"cb355538-30fa29680f15d123c598.js","size":4084},{"name":"component---src-pages-about-tsx-da83a42f597eadc8762b.js","size":7595}],"filteredAssets":0,"assetsSize":11679,"filteredAuxiliaryAssets":3,"auxiliaryAssetsSize":1473411},"component---src-pages-index-tsx":{"name":"component---src-pages-index-tsx","assets":[{"name":"cb355538-30fa29680f15d123c598.js","size":4084},{"name":"component---src-pages-index-tsx-58e803a52338668efe1b.js","size":6253}],"filteredAssets":0,"assetsSize":10337,"filteredAuxiliaryAssets":2,"auxiliaryAssetsSize":1432385},"component---src-pages-projects-tsx":{"name":"component---src-pages-projects-tsx","assets":[{"name":"cb355538-30fa29680f15d123c598.js","size":4084},{"name":"component---src-pages-projects-tsx-fe37d36cfc4dde35542d.js","size":7803}],"filteredAssets":0,"assetsSize":11887,"filteredAuxiliaryAssets":2,"auxiliaryAssetsSize":1435253}},"assetsByChunkName":{"app":["webpack-runtime-e0c745ab160e06106336.js","framework-d3538fe65447818bc523.js","styles.da9a523e30d00bd413e8.css","app-924d945b4d9342038a0b.js"],"component---src-pages-404-tsx":["cb355538-30fa29680f15d123c598.js","component---src-pages-404-tsx-18d03eee48b374ad9661.js"],"component---src-pages-about-tsx":["cb355538-30fa29680f15d123c598.js","component---src-pages-about-tsx-da83a42f597eadc8762b.js"],"component---src-pages-index-tsx":["cb355538-30fa29680f15d123c598.js","component---src-pages-index-tsx-58e803a52338668efe1b.js"],"component---src-pages-projects-tsx":["cb355538-30fa29680f15d123c598.js","component---src-pages-projects-tsx-fe37d36cfc4dde35542d.js"]},"childAssetsByChunkName":{}}