{"name":"build-javascript","namedChunkGroups":{"app":{"name":"app","assets":[{"name":"webpack-runtime-72fe6638e422281945d9.js","size":3779},{"name":"framework-d3538fe65447818bc523.js","size":140769},{"name":"styles.644826b8d21f3eb44922.css","size":9976},{"name":"app-93b2f000bff1a7a7b55d.js","size":61351}],"filteredAssets":0,"assetsSize":215875,"filteredAuxiliaryAssets":5,"auxiliaryAssetsSize":1006501},"component---src-pages-404-tsx":{"name":"component---src-pages-404-tsx","assets":[{"name":"cb355538-30fa29680f15d123c598.js","size":4084},{"name":"component---src-pages-404-tsx-16d72c800b23825f18e5.js","size":6117}],"filteredAssets":0,"assetsSize":10201,"filteredAuxiliaryAssets":2,"auxiliaryAssetsSize":1432408},"component---src-pages-about-tsx":{"name":"component---src-pages-about-tsx","assets":[{"name":"cb355538-30fa29680f15d123c598.js","size":4084},{"name":"component---src-pages-about-tsx-f9d0539175b2a86c8d2b.js","size":7450}],"filteredAssets":0,"assetsSize":11534,"filteredAuxiliaryAssets":3,"auxiliaryAssetsSize":1473411},"component---src-pages-index-tsx":{"name":"component---src-pages-index-tsx","assets":[{"name":"cb355538-30fa29680f15d123c598.js","size":4084},{"name":"component---src-pages-index-tsx-6986a72bf62acc7afbd9.js","size":6178}],"filteredAssets":0,"assetsSize":10262,"filteredAuxiliaryAssets":2,"auxiliaryAssetsSize":1432380},"component---src-pages-projects-tsx":{"name":"component---src-pages-projects-tsx","assets":[{"name":"cb355538-30fa29680f15d123c598.js","size":4084},{"name":"component---src-pages-projects-tsx-32c0ffd58ebefdcd73f9.js","size":8461}],"filteredAssets":0,"assetsSize":12545,"filteredAuxiliaryAssets":2,"auxiliaryAssetsSize":1436609}},"assetsByChunkName":{"app":["webpack-runtime-72fe6638e422281945d9.js","framework-d3538fe65447818bc523.js","styles.644826b8d21f3eb44922.css","app-93b2f000bff1a7a7b55d.js"],"component---src-pages-404-tsx":["cb355538-30fa29680f15d123c598.js","component---src-pages-404-tsx-16d72c800b23825f18e5.js"],"component---src-pages-about-tsx":["cb355538-30fa29680f15d123c598.js","component---src-pages-about-tsx-f9d0539175b2a86c8d2b.js"],"component---src-pages-index-tsx":["cb355538-30fa29680f15d123c598.js","component---src-pages-index-tsx-6986a72bf62acc7afbd9.js"],"component---src-pages-projects-tsx":["cb355538-30fa29680f15d123c598.js","component---src-pages-projects-tsx-32c0ffd58ebefdcd73f9.js"]},"childAssetsByChunkName":{}}